textpy/__init__.py
textpy/_typing.py
textpy/_version.py
textpy/abc.py
textpy/core.py
textpy/css.py
textpy/doc.py
textpy/imports.py
textpy/interaction.py
textpy/texttree.py
textpy/utils/__init__.py
textpy/utils/auto_docstring_custom.mustache
textpy/utils/validator.py
textpy-0.2.3.dist-info/METADATA
textpy-0.2.3.dist-info/WHEEL
textpy-0.2.3.dist-info/licenses/LICENSE
textpy-0.2.3.dist-info/RECORD
