Metadata-Version: 2.4
Name: textpy
Version: 0.2.3
Summary: Reads a python module and statically analyzes it.
Project-URL: Documentation, https://github.com/Chitaoji/textpy/blob/main/README.md
Project-URL: Repository, https://github.com/Chitaoji/textpy/
Author-email: Chitaoji <2360742040@qq.com>
Maintainer-email: Chitaoji <2360742040@qq.com>
License-Expression: BSD-3-Clause
License-File: LICENSE
Keywords: text-find-and-replace
Classifier: Programming Language :: Python :: 3
Classifier: Programming Language :: Python :: 3.12
Requires-Python: >=3.12
Requires-Dist: black
Requires-Dist: colorama
Requires-Dist: htmlmaster
Requires-Dist: lazyr
Requires-Dist: re-extensions
Requires-Dist: typing-extensions
